assets/logo.png
typed_argparser/__init__.py
typed_argparser/config.py
typed_argparser/constants.py
typed_argparser/exceptions.py
typed_argparser/fields.py
typed_argparser/formatter.py
typed_argparser/groups.py
typed_argparser/libs.py
typed_argparser/parser.py
typed_argparser/types.py
typed_argparser/utils.py
typed_argparser/validators.py
typed_argparser-1.0.0.post3.dist-info/LICENSE
typed_argparser-1.0.0.post3.dist-info/METADATA
typed_argparser-1.0.0.post3.dist-info/WHEEL
typed_argparser-1.0.0.post3.dist-info/top_level.txt
typed_argparser-1.0.0.post3.dist-info/RECORD
