Metadata-Version: 2.1
Name: typed_argparser
Version: 1.0.0.post3
Summary: Simplify command line argument parsing & validation with type hints
Author-email: Ankit Jain <ajatkj.dev@gmail.com>
License: MIT
Project-URL: Repository, https://github.com/ajatkj/typed_argparser
Keywords: typed,argparse,argparser,argparse-typed
Classifier: License :: OSI Approved :: MIT License
Classifier: Programming Language :: Python :: 3 :: Only
Classifier: Programming Language :: Python :: 3.8
Classifier: Programming Language :: Python :: 3.9
Classifier: Programming Language :: Python :: 3.10
Classifier: Programming Language :: Python :: 3.11
Classifier: Programming Language :: Python :: 3.12
Classifier: Typing :: Typed
Requires-Python: >=3.8
License-File: LICENSE
Requires-Dist: typing-extensions <5.0.0,>=4.7.0
